LICENSE
MANIFEST.in
README.md
requirements.txt
setup.py
allmusic/__init__.py
allmusic.egg-info/PKG-INFO
allmusic.egg-info/SOURCES.txt
allmusic.egg-info/dependency_links.txt
allmusic.egg-info/requires.txt
allmusic.egg-info/top_level.txt
test/__init__.py
test/test_allmusic.py