Metadata-Version: 2.1
Name: allmusic
Version: 0.0.1
Summary: AllMusic review scraper
Home-page: https://github.com/fortes/allmusic
Author: Filipe Fortes
Author-email: accounts@fortes.com
License: MIT
Platform: ALL
Classifier: License :: OSI Approved :: MIT License
Classifier: Operating System :: OS Independent
Classifier: Programming Language :: Python :: 3
Classifier: Topic :: Internet :: WWW/HTTP :: Indexing/Search
